racing_report_package/__init__.py
racing_report_package/racing_report.py
racing_report_swaghettie-0.0.3.dist-info/METADATA
racing_report_swaghettie-0.0.3.dist-info/WHEEL
racing_report_swaghettie-0.0.3.dist-info/licenses/LICENSE
racing_report_swaghettie-0.0.3.dist-info/RECORD
