Metadata-Version: 2.1
Name: racing_report_SWAGhettie
Version: 0.0.3
Summary: App that sorts racing results and store it in logs
Project-URL: Homepage, https://git.foxminded.ua/foxstudent104424/task-6-report-of-monaco-2018-racing/-/merge_requests
Author-email: Ihor Prokopenko <scaryscreamerg@gmail.com>
License-File: LICENSE
Classifier: Operating System :: OS Independent
Classifier: Programming Language :: Python :: 3
Requires-Python: >=3.11.0
